geomatch/__init__.py
geomatch/cli.py
geomatch/geomatch.py
geomatch/haversine.py
geomatch/mongo.py
geomatch/parallel.py
geomatch/plot.py
geomatch-0.3.0.dist-info/METADATA
geomatch-0.3.0.dist-info/WHEEL
geomatch-0.3.0.dist-info/entry_points.txt
geomatch-0.3.0.dist-info/RECORD
