Metadata-Version: 2.1
Name: geomatch
Version: 0.3.0
Summary: Matching two satellites up in space.
Requires-Python: >=3.8
Requires-Dist: click>=8.1.7
Requires-Dist: folium>=0.14.0
Requires-Dist: icc-rt>=2020.0.133
Requires-Dist: numba>=0.57.1
Requires-Dist: pandas>=2.0.3
Requires-Dist: pymongo==3.13.0
Requires-Dist: shapely>=2.0.1
